{
    "executionRoleArn": null,
    "containerDefinitions": [
        {
            "name": "otoraja-biz",
            "image": "<IMAGE1_NAME>",
            "portMappings": [
                {
                    "containerPort": 3000,
                    "hostPort": 3000,
                    "protocol": "tcp"
                }
            ],
            "essential": true
        }
    ],
    "requiresCompatibilities": [
        "FARGATE"
    ],
    "networkMode": "awsvpc",
    "cpu": "1024",
    "memory": "2048",
    "family": "otoraja-biz"
}
